{
  "id": "b396fde0-1aa2-11e6-a178-4b15f5ed2cab",
  "name": "BlackDuckHubScan",
  "friendlyName": "Black Duck Hub Scan",
  "description": "Execute a Black Duck Hub scan against your build",
  "author": "Black Duck Software, Inc.",
  "category": "Utility",
  "visibility": [
    "Build",
    "Release"
  ],
  "demands": [],
  "version": {
    "Major": "0",
    "Minor": "1",
    "Patch": "0"
  },
  "minimumAgentVersion": "1.95.0",
  "instanceNameFormat": "Execute a Black Duck Hub scan against your build $(message)",
  "inputs": [
    {
      "name": "HubUsername",
      "type": "string",
      "label": "Username",
      "defaultValue": "",
      "required": true,
      "helpMarkDown": "The username to access your Black Duck Hub instance."
    },
    {
      "name": "HubPassword",
      "type": "string",
      "label": "Password",
      "defaultValue": "",
      "required": true,
      "helpMarkDown": "The password to access your Black Duck Hub instance."
    },
    {
      "name": "HubUrl",
      "type": "string",
      "label": "Server URL",
      "defaultValue": "",
      "required": true,
      "helpMarkDown": "Provide the URL for your Black Duck Hub Server - please include the port if other than 80 (http) or 443 (https)"
    },
    {
      "name": "HubProjectName",
      "type": "string",
      "label": "Project Name",
      "defaultValue": "",
      "required": true
    },
    {
      "name": "HubRelease",
      "type": "string",
      "label": "Project Version",
      "defaultValue": "",
      "required": true
    },
    {
      "name": "HubFailOnPolicyViolation",
      "type": "boolean",
      "label": "Fail the Build for Hub Policy Violations",
      "required": false
    },
    {
      "name": "HubScanTimeout",
      "type": "string",
      "label": "Scan Timeout",
      "defaultValue": "5",
      "required": true,
      "helpMarkDown": "In minutes (set to zero for no timeout.)"
    }
  ],
  "execution": {
    "PowerShell": {
      "target": "$(currentDirectory)\\tfs-scan-executor.ps1",
      "argumentFormat": "",
      "workingDirectory": "$(currentDirectory)"
    }
  }
}